{
  "id": "filter-duotone",
  "name": "Filter: Duotone",
  "description": "A two-color duotone for any photo — shadows one color, highlights another.",
  "version": "1.1.0",
  "engineVersion": "^1.0.0",
  "status": "official",
  "category": "designer",
  "tags": ["photo", "filter", "duotone", "color", "effect"],
  "examples": [
    { "label": "Pine & peach", "values": { "colorFg": "#0c322c", "colorBg": "#fcb244" } },
    { "label": "Jade duotone", "values": { "colorFg": "#0c322c", "colorBg": "#30ba78" } },
    { "label": "Ocean duotone", "values": { "colorFg": "#000000", "colorBg": "#0a9bd6" } },
    { "label": "Teal & mint", "values": { "colorFg": "#0c322c", "colorBg": "#2fb9a0" } },
    { "label": "Electric duotone", "values": { "colorFg": "#000000", "colorBg": "#2453ff" } },
    { "label": "Sunset duotone", "values": { "colorFg": "#0c322c", "colorBg": "#fe7c3f" } }
  ],
  "render": {
    "width": 1080,
    "height": 1080,
    "formats": ["png", "jpg", "webp", "svg", "gif", "apng", "webm", "mp4"],
    "actions": ["copy", "download", "save"],
    "video": { "wait": 0, "duration": 5 }
  },
  "hooks": {
    "onInit": true,
    "onInput": true,
    "onFrame": true
  },
  "inputs": [
    {
      "id": "bgImage",
      "label": "Background image",
      "type": "asset",
      "assetType": "raster",
      "allowUpload": true
    },
    {
      "id": "colorFg",
      "label": "Shadow color",
      "type": "color",
      "default": "#0c322c"
    },
    {
      "id": "colorBg",
      "label": "Highlight color",
      "type": "color",
      "default": "#ffd3bd"
    },
    {
      "id": "imageFraming",
      "label": "Zoom & Position",
      "section": "Position",
      "help": "Zoom scales the photo up; X / Y pan it within the frame (like object-position). Drag a label or type a value.",
      "type": "vector",
      "fields": [
        { "id": "zoom", "label": "Zoom", "min": 100, "max": 400, "step": 1, "default": 100 },
        { "id": "x",    "label": "X",    "min": 0,   "max": 100, "step": 1, "default": 50  },
        { "id": "y",    "label": "Y",    "min": 0,   "max": 100, "step": 1, "default": 50  }
      ]
    },
    { "id": "hue", "label": "Hue", "section": "Colour", "type": "number", "display": "slider", "default": 0, "min": -180, "max": 180, "step": 1, "help": "Rotate every colour around the wheel." },
    { "id": "saturation", "label": "Saturation", "section": "Colour", "type": "number", "display": "slider", "default": 100, "min": 0, "max": 200, "step": 1, "help": "0 = greyscale · 100 = original · 200 = vivid." },
    { "id": "lightness", "label": "Lightness", "section": "Colour", "type": "number", "display": "slider", "default": 0, "min": -100, "max": 100, "step": 1, "help": "Lift toward white or sink toward black." },
    { "id": "treatmentColor", "label": "Colour treatment", "section": "Colour", "type": "color", "default": "", "help": "Blend a colour over the result. Leave empty for none." },
    { "id": "blendMode", "label": "Blend mode", "section": "Colour", "type": "select", "default": "multiply", "options": [
      { "value": "normal", "label": "Normal" }, { "value": "multiply", "label": "Multiply" }, { "value": "screen", "label": "Screen" },
      { "value": "overlay", "label": "Overlay" }, { "value": "darken", "label": "Darken" }, { "value": "lighten", "label": "Lighten" },
      { "value": "color-dodge", "label": "Colour dodge" }, { "value": "color-burn", "label": "Colour burn" },
      { "value": "hard-light", "label": "Hard light" }, { "value": "soft-light", "label": "Soft light" },
      { "value": "difference", "label": "Difference" }, { "value": "exclusion", "label": "Exclusion" },
      { "value": "hue", "label": "Hue" }, { "value": "saturation", "label": "Saturation" }, { "value": "color", "label": "Colour" }, { "value": "luminosity", "label": "Luminosity" }
    ], "help": "How the treatment colour mixes with the image." },
    { "id": "treatmentIntensity", "label": "Intensity", "section": "Colour", "type": "number", "display": "slider", "default": 20, "min": 0, "max": 100, "step": 1, "help": "Opacity of the colour overlay." },
    { "id": "width",  "label": "Width",  "type": "number", "default": 1080, "min": 1, "max": 8000, "group": "export" },
    { "id": "height", "label": "Height", "type": "number", "default": 1080, "min": 1, "max": 8000, "group": "export" },
    {
      "id": "noFilter",
      "label": "No filter (show raw)",
      "section": "Overlay",
      "type": "boolean",
      "default": false,
      "help": "Show the original photo or live camera feed untouched — handy for placing just a logo / lower-third over the raw footage."
    },
    {
      "id": "showLogo",
      "label": "SUSE logo overlay",
      "section": "Overlay",
      "type": "boolean",
      "default": false,
      "help": "Overlay the SUSE logo on the result. Off by default."
    },
    {
      "id": "logoPosition",
      "label": "Logo position",
      "section": "Overlay",
      "type": "select",
      "default": "top-right",
      "showIf": { "showLogo": true },
      "options": [
        { "value": "top-left", "label": "Top left" },
        { "value": "top-right", "label": "Top right" },
        { "value": "bottom-left", "label": "Bottom left" },
        { "value": "bottom-right", "label": "Bottom right" },
        { "value": "top", "label": "Top centre" },
        { "value": "bottom", "label": "Bottom centre" },
        { "value": "center", "label": "Centre" },
        { "value": "full", "label": "Full (watermark)" }
      ]
    },
    {
      "id": "logoStyle",
      "label": "Logo colour",
      "section": "Overlay",
      "type": "select",
      "default": "white",
      "showIf": { "showLogo": true },
      "options": [
        { "value": "white", "label": "White" },
        { "value": "green", "label": "Green" },
        { "value": "black", "label": "Black" }
      ],
      "help": "White and green read on dark or busy footage; black suits light backgrounds."
    },
    {
      "id": "logoScale",
      "label": "Logo size",
      "section": "Overlay",
      "type": "number",
      "display": "slider",
      "default": 1,
      "min": 0.25,
      "max": 3,
      "step": 0.05,
      "showIf": { "showLogo": true },
      "help": "Scale the logo up or down."
    },
    {
      "id": "lowerThird",
      "label": "Lower-third name card",
      "section": "Overlay",
      "type": "boolean",
      "default": false,
      "help": "A gently-animated name card that draws in over the footage. Uses your profile name & headshot."
    },
    {
      "id": "ltTheme",
      "label": "Card style",
      "section": "Overlay",
      "type": "select",
      "default": "bar",
      "showIf": { "lowerThird": true },
      "options": [
        { "value": "bar", "label": "SUSE brand bar" },
        { "value": "minimal", "label": "Minimal" },
        { "value": "glass", "label": "Glass" }
      ]
    },
    {
      "id": "ltPosition",
      "label": "Card position",
      "section": "Overlay",
      "type": "select",
      "default": "left",
      "showIf": { "lowerThird": true },
      "options": [
        { "value": "left", "label": "Bottom left" },
        { "value": "center", "label": "Bottom centre" },
        { "value": "right", "label": "Bottom right" }
      ]
    },
    {
      "id": "firstname",
      "label": "First name",
      "section": "Overlay",
      "type": "text",
      "default": "",
      "bindToProfile": "firstname",
      "showIf": { "lowerThird": true }
    },
    {
      "id": "lastname",
      "label": "Last name",
      "section": "Overlay",
      "type": "text",
      "default": "",
      "bindToProfile": "lastname",
      "showIf": { "lowerThird": true }
    },
    {
      "id": "title",
      "label": "Role / subtitle",
      "section": "Overlay",
      "type": "text",
      "default": "",
      "showIf": { "lowerThird": true },
      "help": "Optional line below the name — e.g. a role or event."
    },
    {
      "id": "nameWeight",
      "label": "Name weight",
      "section": "Overlay",
      "type": "number",
      "display": "slider",
      "min": 100,
      "max": 900,
      "step": 100,
      "default": 500,
      "showIf": { "lowerThird": true },
      "help": "Font weight of the name line (100 Thin → 900 Black)."
    },
    {
      "id": "subtitleWeight",
      "label": "Subtitle weight",
      "section": "Overlay",
      "type": "number",
      "display": "slider",
      "min": 100,
      "max": 900,
      "step": 100,
      "default": 500,
      "showIf": { "lowerThird": true },
      "help": "Font weight of the role / subtitle line (100 Thin → 900 Black)."
    },
    {
      "id": "ltHeadshot",
      "label": "Headshot (optional)",
      "section": "Overlay",
      "type": "asset",
      "assetType": "raster",
      "allowUpload": true,
      "showIf": { "lowerThird": true },
      "help": "Defaults to your profile headshot. Pick or upload another to override."
    }
  ]
}
